LICENSE
README.md
setup.py
pyfanotify/__init__.py
pyfanotify.egg-info/PKG-INFO
pyfanotify.egg-info/SOURCES.txt
pyfanotify.egg-info/dependency_links.txt
pyfanotify.egg-info/top_level.txt
src/ext.c