Metadata-Version: 2.1
Name: pyfanotify
Version: 0.1.0
Summary: Python wrapper for Linux fanotify
Home-page: https://github.com/baskiton/pyfanotify
Author: Alexander Baskikh
Author-email: baskiton@gmail.com
License: MIT
Project-URL: Source, https://github.com/baskiton/pyfanotify
Project-URL: Bug Tracker, https://github.com/baskiton/pyfanotify/issues
Keywords: linux kernel fanotify
Platform: UNKNOWN
Classifier: License :: OSI Approved :: MIT License
Classifier: Programming Language :: Python :: 3
Classifier: Operating System :: POSIX :: Linux
Classifier: Topic :: System :: Operating System Kernels :: Linux
Requires-Python: >=3.6
License-File: LICENSE
